property_manager3/__init__.py
property_manager3/sphinx.py
property_manager3/tests.py
property_manager3-2.3.1.dist-info/LICENSE.txt
property_manager3-2.3.1.dist-info/METADATA
property_manager3-2.3.1.dist-info/WHEEL
property_manager3-2.3.1.dist-info/top_level.txt
property_manager3-2.3.1.dist-info/RECORD
